Verilog/II-semester/Labs/fifo.v
module fifo #(
   parameter DATA_WIDTH = 8, // can keep up to 2⁸=265 bits data
   parameter ADDR_WIDTH = 4 // there are 2⁴=16 positions
) (
    input clk, rst, wr_en, rd_en,
    input [DATA_WIDTH-1 : 0] data_in,
    output full, empty,
    output reg [DATA_WIDTH - 1 : 0] data_out
);
    reg [DATA_WIDTH : 0] mem [ (1 << ADDR_WIDTH) - 1 : 0];
    reg [ADDR_WIDTH : 0] wr_pt, rd_pt;

    assign empty = (wr_pt == rd_pt);
    assign full = (wr_pt[ADDR_WIDTH - 1 : 0] == rd_pt[ADDR_WIDTH - 1 : 0]) && (wr_pt[ADDR_WIDTH] != rd_pt[ADDR_WIDTH]);

    always @(posedge clk) begin
        if(rst) begin
            wr_pt <= 0;
            rd_pt <= 0;
            data_out <= 0;
        end
        else begin
            if(wr_en && !full) begin
                mem[wr_pt[ADDR_WIDTH - 1 : 0]] <= data_in;
                wr_pt <= wr_pt + 1;
            end

            if(rd_en && !empty) begin
                data_out <= mem[rd_pt[ADDR_WIDTH - 1 : 0]];
                rd_pt <= rd_pt + 1;
            end
        end
    end
endmodule

module fifo_tb;
    parameter DATA_WIDTH = 8;
    parameter ADDR_WIDTH = 2;
    reg clk, rst, wr_en, rd_en;
    reg [DATA_WIDTH - 1 : 0] data_in;
    wire full, empty;
    wire [DATA_WIDTH - 1 : 0] data_out;

    fifo #(.DATA_WIDTH(DATA_WIDTH), .ADDR_WIDTH(ADDR_WIDTH)) uut(
        .clk(clk), .rst(rst), .wr_en(wr_en), .rd_en(rd_en), .data_in(data_in), .full(full), .empty(empty), .data_out(data_out)
    );

    always #5 clk = ~clk;
    integer i;

    initial begin
        $monitor("Time\t=%0t | rst=%b | wr=%b | rd=%b | full=%b | empty=%b | data_in=%d (%b) | data_out=%d (%b)",
            $time, rst, wr_en, rd_en, full, empty, data_in, data_in, data_out, data_out);
    end
    
    initial begin
        clk = 0; rst = 1; wr_en = 0; rd_en = 0; data_in = 0;
        #23 rst = 0;
        for(i=1; i <= (2 << ADDR_WIDTH); i = i+1) begin
            @(negedge clk);
            if(!full) begin
                wr_en = 1;
                data_in = i*2;
            end
        end

        @(negedge clk);
        data_in = 8'd9;

        @(negedge clk);
        wr_en = 0;

        #20;

        while (!empty) begin
            @(negedge clk);
            rd_en = 1;
        end

        @(negedge clk);
        rd_en = 0;
        
        #50 $finish;
    end
    // initial begin
    //     $dumpfile("fifo.vcd");
    //     $dumpvars(0, fifo_tb);
    // end
endmodule

Verilog/II-semester/Labs/fifo.vcd
$date
	Thu Apr  2 15:12:18 2026
$end
$version
	Icarus Verilog
$end
$timescale
	1s
$end
$scope module fifo_tb $end
$var wire 1 ! full $end
$var wire 1 " empty $end
$var wire 8 # data_out [7:0] $end
$var parameter 32 $ ADDR_WIDTH $end
$var parameter 32 % DATA_WIDTH $end
$var reg 1 & clk $end
$var reg 8 ' data_in [7:0] $end
$var reg 1 ( rd_en $end
$var reg 1 ) rst $end
$var reg 1 * wr_en $end
$var integer 32 + i [31:0] $end
$scope module uut $end
$var wire 1 & clk $end
$var wire 8 , data_in [7:0] $end
$var wire 1 ! full $end
$var wire 1 ( rd_en $end
$var wire 1 ) rst $end
$var wire 1 * wr_en $end
$var wire 1 " empty $end
$var parameter 32 - ADDR_WIDTH $end
$var parameter 32 . DATA_WIDTH $end
$var reg 8 / data_out [7:0] $end
$var reg 3 0 rd_pt [2:0] $end
$var reg 3 1 wr_pt [2:0] $end
$upscope $end
$upscope $end
$enddefinitions $end
$comment Show the parameter values. $end
$dumpall
b1000 .
b10 -
b1000 %
b10 $
$end
#0
$dumpvars
bx 1
bx 0
bx /
b0 ,
bx +
0*
1)
0(
b0 '
0&
bx #
x"
x!
$end
#5
0!
b0 #
b0 /
1"
b0 0
b0 1
1&
#10
0&
#15
1&
#20
0&
#23
b1 +
0)
#25
1&
#30
b10 +
b10 '
b10 ,
1*
0&
#35
0"
b1 1
1&
#40
b11 +
b100 '
b100 ,
0&
#45
b10 1
1&
#50
b100 +
b110 '
b110 ,
0&
#55
b11 1
1&
#60
b101 +
b1000 '
b1000 ,
0&
#65
1!
b100 1
1&
#70
b110 +
0&
#75
1&
#80
b111 +
0&
#85
1&
#90
b1000 +
0&
#95
1&
#100
b1001 +
0&
#105
1&
#110
b1001 '
b1001 ,
0&
#115
1&
#120
0*
0&
#125
1&
#130
0&
#135
1&
#140
1(
0&
#145
0!
b1 0
b10 #
b10 /
1&
#150
0&
#155
b10 0
b100 #
b100 /
1&
#160
0&
#165
b11 0
b110 #
b110 /
1&
#170
0&
#175
1"
b100 0
b1000 #
b1000 /
1&
#180
0&
#185
1&
#190
0(
0&
