Verilog/exam/mealy.v
// 101 Assume negedge clock negedge set

module fsm_mealy (
    input x, clk, set, output reg y
);
    parameter s0 = 2'b00; // start
    parameter s1 = 2'b01; // 1
    parameter s2 = 2'b10; // 10;
    
    reg [1:0] state, next_state;
    
    always @(negedge clk or negedge set) begin
        if(!set)
            state <= s0;
        else
            state <= next_state;
    end

    always @(*) begin
        case (state)
            s0 : next_state = (x == 1) ? s1 : s0;
            s1 : next_state = (x == 0) ? s2 : s1;
            s2 : next_state = (x == 1) ? s1 : s0;
            default: next_state = s0;
        endcase
    end
    always @(*) begin
        y = (state == s2 && x == 1);
    end
endmodule

module fsm_mealy_tb;
    reg x, clk, set;
    wire y;
    fsm_mealy uut(.x(x), .clk(clk), .set(set), .y(y));
    
    always #5 clk = ~clk;

    initial begin
        $monitor("Time=%0t | set=%b | x=%b | state=%b | y=%b", $time, set, x, uut.state, y);
        clk = 1; x = 0; set = 0;
        #13 set = 1;
        @(posedge clk) x = 1;
        @(posedge clk) x = 0;
        @(posedge clk) x = 1;
        #27 $finish;
    end
    initial begin
        $dumpfile("mealy.vcd");
        $dumpvars(0, fsm_mealy_tb);
    end
endmodule

Verilog/exam/mealy.vcd
$date
	Wed Apr  8 11:22:23 2026
$end
$version
	Icarus Verilog
$end
$timescale
	1s
$end
$scope module fsm_mealy_tb $end
$var wire 1 ! y $end
$var reg 1 " clk $end
$var reg 1 # set $end
$var reg 1 $ x $end
$scope module uut $end
$var wire 1 " clk $end
$var wire 1 # set $end
$var wire 1 $ x $end
$var parameter 2 % s0 $end
$var parameter 2 & s1 $end
$var parameter 2 ' s2 $end
$var reg 2 ( next_state [1:0] $end
$var reg 2 ) state [1:0] $end
$var reg 1 ! y $end
$upscope $end
$upscope $end
$enddefinitions $end
$comment Show the parameter values. $end
$dumpall
b10 '
b1 &
b0 %
$end
#0
$dumpvars
b0 )
b0 (
0$
0#
1"
0!
$end
#5
0"
#10
1"
#13
1#
#15
0"
#20
b1 (
1$
1"
#25
b1 )
0"
#30
b10 (
0$
1"
#35
b0 (
b10 )
0"
#40
1!
b1 (
1$
1"
#45
0!
b1 )
0"
#50
b0 )
1"
0#
#55
0"
#60
1"
#63
1#
#65
b1 )
0"
#70
1"
#75
0"
#80
b10 (
0$
1"
#85
b0 (
b10 )
0"
#90
1!
b1 (
1$
1"
#95
0!
b1 )
0"
