Verilog/I-semester/and-gate.sv
module and_gate(
    input a,b,c,d,
    output y
);
    assign y = a & b & c & d;
endmodule

module test_and ();
    reg a,b,c,d;
    wire y;
    and_gate dut(a,b,c,d,y);
    initial begin
        $dumpfile("./vcd_files/and_wave.vcd");
        $dumpvars(0, test_and);
        for(int i=0;i<16;i++) begin
            {a,b,c,d} = i[3:0];
            #5;
            $display("a=%b b=%b c=%b d=%b y=%b",a,b,c,d,y);
        end
    end
    
endmodule

Verilog/I-semester/vcd_files/and_wave.vcd
$date
	Sat Jan 17 14:57:51 2026
$end
$version
	Icarus Verilog
$end
$timescale
	1s
$end
$scope module test_and $end
$var wire 1 ! y $end
$var reg 1 " a $end
$var reg 1 # b $end
$var reg 1 $ c $end
$var reg 1 % d $end
$scope module dut $end
$var wire 1 " a $end
$var wire 1 # b $end
$var wire 1 $ c $end
$var wire 1 % d $end
$var wire 1 ! y $end
$upscope $end
$scope begin $ivl_for_loop0 $end
$var integer 32 & i [31:0] $end
$upscope $end
$upscope $end
$enddefinitions $end
$comment Show the parameter values. $end
$dumpall
$end
#0
$dumpvars
b0 &
0%
0$
0#
0"
0!
$end
#5
1%
b1 &
#10
1$
0%
b10 &
#15
1%
b11 &
#20
1#
0$
0%
b100 &
#25
1%
b101 &
#30
1$
0%
b110 &
#35
1%
b111 &
#40
1"
0#
0$
0%
b1000 &
#45
1%
b1001 &
#50
1$
0%
b1010 &
#55
1%
b1011 &
#60
1#
0$
0%
b1100 &
#65
1%
b1101 &
#70
1$
0%
b1110 &
#75
1!
1%
b1111 &
#80
b10000 &
