Verilog/I-semester/dff.sv
module dff (
    input wire d,
    input wire clk,
    output reg q
);
    always @(posedge clk) begin
        q <= d;
    end
    
endmodule

`timescale 1ns/1ns

module tb_dff();
    reg d;
    reg clk;
    wire q;
    dff uut(
        .d(d),
        .clk(clk),
        .q(q)
    );
    initial begin
        clk = 0;
        forever #5 clk = ~clk;
    end
    initial begin
    $dumpfile("./vcd_files/dff_wave.vcd"); // Ստեղծում է ֆայլը, որտեղ պահվելու են գրաֆիկները
    $dumpvars(0, tb_dff);      // Ասում է՝ պահիր tb_dff-ի բոլոր լարերի փոփոխությունները
    
    $display("Time\t clk\t data\t q");
    $monitor("%0t\t %b\t %b\t %b", $time, clk, d, q);

    d = 0;
    #7 d = 1;
    #10 d = 0;
    #10 d = 1;
    #20 $finish;
end
endmodule

Verilog/I-semester/vcd_files/dff_wave.vcd
$date
	Sat Jan 17 07:44:39 2026
$end
$version
	Icarus Verilog
$end
$timescale
	1ns
$end
$scope module tb_dff $end
$var wire 1 ! q $end
$var reg 1 " clk $end
$var reg 1 # d $end
$scope module uut $end
$var wire 1 " clk $end
$var wire 1 # d $end
$var reg 1 ! q $end
$upscope $end
$upscope $end
$enddefinitions $end
$comment Show the parameter values. $end
$dumpall
$end
#0
$dumpvars
0#
0"
x!
$end
#5
0!
1"
#7
1#
#10
0"
#15
1!
1"
#17
0#
#20
0"
#25
0!
1"
#27
1#
#30
0"
#35
1!
1"
