Verilog/II-semester/Test/test_mealy.v
module seq_detector(input clk, reset, x, output reg y);
    parameter S0 = 2'b00;
    parameter S1 = 2'b01;
    parameter S2 = 2'b10;

    reg [1:0] state, next_state;

    always @(posedge clk or posedge reset) begin
        if(reset) begin
          state <= S0;
        end
        else begin
          state <= next_state;
        end
    end

    always @(*) begin
        y = 0;
        case (state)
           S0 : next_state = (x == 1) ? S1 : S0;
           S1 : next_state = (x == 0) ? S2 : S1;
           S2 : begin
                if(x == 1) begin
                  next_state = S1;
                  y = 1;
                end
                else begin
                  next_state = S0;
                  y = 0;
                end
           end
            default: next_state = S0;
        endcase
    end
endmodule

module seq_detector_tb;
    reg clk, reset, x;
    wire y;

    seq_detector uut(.clk(clk), .x(x), .reset(reset), .y(y));
    always #5 clk = ~clk;

    initial begin
        $monitor("Time=%0t | x=%b | reset=%b | state=%b | y=%b", $time, x, reset, uut.state, y);
        clk = 0; reset = 1; x = 0;
        #12 reset = 0;

        @(negedge clk) x = 1;
        @(negedge clk) x = 0;
        @(negedge clk) x = 1;
        #10; 
        $finish;
    end
    initial begin
        $dumpfile("test_mealy.vcd");
        $dumpvars(0, seq_detector_tb);
    end
endmodule

Verilog/II-semester/Test/test_mealy.vcd
$date
	Fri May 15 17:46:56 2026
$end
$version
	Icarus Verilog
$end
$timescale
	1s
$end
$scope module seq_detector_tb $end
$var wire 1 ! y $end
$var reg 1 " clk $end
$var reg 1 # reset $end
$var reg 1 $ x $end
$scope module uut $end
$var wire 1 " clk $end
$var wire 1 # reset $end
$var wire 1 $ x $end
$var parameter 2 % S0 $end
$var parameter 2 & S1 $end
$var parameter 2 ' S2 $end
$var reg 2 ( next_state [1:0] $end
$var reg 2 ) state [1:0] $end
$var reg 1 ! y $end
$upscope $end
$upscope $end
$enddefinitions $end
$comment Show the parameter values. $end
$dumpall
b10 '
b1 &
b0 %
$end
#0
$dumpvars
b0 )
b0 (
0$
1#
0"
0!
$end
#5
1"
#10
0"
#12
0#
#15
1"
#20
b1 (
1$
0"
#25
b1 )
1"
#30
b10 (
0$
0"
#35
b0 (
b10 )
1"
#40
1!
b1 (
1$
0"
#45
0!
b1 )
1"
