Verilog/II-semester/Draft/alu-4.v
module alu (
    a,b, opcode, result, zero
);
    input [3:0] a,b;
    input [2:0] opcode;
    output reg [3:0] result;
    output reg zero;

    always @(*) begin
        case (opcode)
            3'b000 : result = a + b;
            3'b001 : result = a - b;
            3'b010 : result = a & b;
            3'b011 : result = a | b;
            3'b100 : result = a ^ b;
            3'b101 : result = a << 1;
            3'b110 : result = a >> 1;
            3'b111 : result = (a == b) ? 4'b0001 : 4'b0000;
            default: result = 4'b000;
        endcase
        zero = (result == 4'b0000);
    end
endmodule

module alu_tb();
    reg [3:0] a,b;
    reg [2:0] opcode;
    wire [3:0] result;
    wire zero;

    alu uut(
        .a(a), .b(b), .opcode(opcode), .result(result), .zero(zero)
    );

    integer i;
    initial begin
    a = 5;
    b = 4;
        for(i=0; i<8; i = i+1) begin
            opcode = i[2:0];
            #10;
        end
        #10;
        $finish;
    end

    initial begin
        $dumpfile("alu.vcd");
        $dumpvars(0, alu_tb);
        $monitor("Time=0%t | a=%d | b=%d | opcode=%b | result=%d | zero=%b", $time, a, b, opcode, result, zero);
    end
endmodule

Verilog/II-semester/Draft/alu.vcd
$date
	Mon Mar  9 12:58:26 2026
$end
$version
	Icarus Verilog
$end
$timescale
	1s
$end
$scope module alu_tb $end
$var wire 1 ! zero $end
$var wire 4 " result [3:0] $end
$var reg 4 # a [3:0] $end
$var reg 4 $ b [3:0] $end
$var reg 3 % opcode [2:0] $end
$var integer 32 & i [31:0] $end
$scope module uut $end
$var wire 4 ' a [3:0] $end
$var wire 4 ( b [3:0] $end
$var wire 3 ) opcode [2:0] $end
$var reg 4 * result [3:0] $end
$var reg 1 ! zero $end
$upscope $end
$upscope $end
$enddefinitions $end
$comment Show the parameter values. $end
$dumpall
$end
#0
$dumpvars
b1001 *
b0 )
b100 (
b101 '
b0 &
b0 %
b100 $
b101 #
b1001 "
0!
$end
#10
b1 "
b1 *
b1 %
b1 )
b1 &
#20
b100 "
b100 *
b10 %
b10 )
b10 &
#30
b101 "
b101 *
b11 %
b11 )
b11 &
#40
b1 "
b1 *
b100 %
b100 )
b100 &
#50
b1010 "
b1010 *
b101 %
b101 )
b101 &
#60
b10 "
b10 *
b110 %
b110 )
b110 &
#70
1!
b0 "
b0 *
b111 %
b111 )
b111 &
#80
b1000 &
