Verilog/II-semester/Draft/dff.v
module dff (
    input clk, rst, d, output q
);
    reg q;
    always @(posedge clk) begin
        if(!rst)
            q <= 1'b0;
        else
            q <= d;
    end
endmodule

module dff_tb();
    reg clk;
    reg rst;
    reg d;
    wire q;
    dff dut(.clk(clk), .rst(rst), .d(d), .q(q));
    always #5 clk = ~clk;
    initial begin
        clk = 0;
        rst = 0;
        d = 0;
        $display("Time\t clk rst d | q");
        $display("-----------------------");
        #15;
        rst = 1;
        d = 1;
        #10;

        d = 0;
        #10;

        d = 1;
        #3;
        d = 0;
        #2;
        d = 1;
        #15;
        rst = 0;
        #10;
        $finish;
    end
    initial begin
        $dumpfile("dff.vcd");
        $dumpvars(0, dff_tb);
        $monitor("%0t\t %b %b %b | %b", $time, clk, rst, d, q);
    end
endmodule

Verilog/II-semester/Draft/dff.vcd
$date
	Fri Feb 27 19:58:46 2026
$end
$version
	Icarus Verilog
$end
$timescale
	1s
$end
$scope module dff_tb $end
$var wire 1 ! q $end
$var reg 1 " clk $end
$var reg 1 # d $end
$var reg 1 $ rst $end
$scope module dut $end
$var wire 1 " clk $end
$var wire 1 # d $end
$var wire 1 $ rst $end
$var reg 1 ! q $end
$upscope $end
$upscope $end
$enddefinitions $end
$comment Show the parameter values. $end
$dumpall
$end
#0
$dumpvars
0$
0#
0"
x!
$end
#5
0!
1"
#10
0"
#15
1!
1"
1#
1$
#20
0"
#25
0!
1"
0#
#30
0"
#35
1!
1"
1#
#38
0#
#40
1#
0"
#45
1"
#50
0"
#55
0!
1"
0$
