Verilog/II-semester/Draft/mealy.v
module mealy (x, clk, reset, y);
    input x, clk, reset;
    output reg y;

    parameter s0 = 3'b000; // start
    parameter s1 = 3'b001; // 0
    parameter s2 = 3'b010; // 01
    parameter s3 = 3'b011; // 010
    parameter s4 = 3'b100; // 0101
    parameter s5 = 3'b101; // 01010
    parameter s6 = 3'b110; // 010100

    reg [2:0] current_state, next_state;

    always @(posedge clk or negedge reset) begin
        // if(!reset) begin
        //     current_state <= s0;        
        // end
        // else begin
        //     current_state <= next_state;
        // end
        current_state <= (!reset) ? s0 : next_state;
    end

    always @(*) begin
        case (current_state)
            s0 : next_state = (x == 1'b0) ? s1 : s0;
            s1 : next_state = (x == 1'b1) ? s2 : s1;
            s2 : next_state = (x == 1'b0) ? s3 : s0;
            s3 : next_state = (x == 1'b1) ? s4 : s1;
            s4 : next_state = (x == 1'b0) ? s5 : s0;
            s5 : next_state = (x == 1'b0) ? s6 : s4;
            s6 : next_state = (x == 1'b1) ? s2 : s1;

            default: next_state = s0;
        endcase
    end

    always @(*) begin
        y = (current_state == s6 && x == 1'b1);
    end
endmodule

module mealy_tb ();
    reg x, clk, reset;
    wire y;
    mealy uut(.x(x), .clk(clk), .reset(reset), .y(y));

    always #5 clk = ~clk; // ամեն 5 ժամանակը մեկ clk-ը փոխի

    initial begin
        clk = 0;
        reset = 0;
        x = 0;

        #2 reset = 1;

        @(negedge clk) x = 0;
        @(negedge clk) x = 1;
        @(negedge clk) x = 0;
        @(negedge clk) x = 1;
        @(negedge clk) x = 0;
        @(negedge clk) x = 0;
        @(negedge clk) x = 1;
        #30;
        $display("Simulation is done!");
        $finish;
    end
    initial begin
        $dumpfile("mealy.vcd");
        $dumpvars(0, mealy_tb);
        // $monitor("Time=%0t | x=%b | state = %b | y=%b", $time, x, uut.current_state, y);
    end
endmodule

Verilog/II-semester/Draft/mealy.vcd
$date
	Sun Mar  8 10:34:21 2026
$end
$version
	Icarus Verilog
$end
$timescale
	1s
$end
$scope module mealy_tb $end
$var wire 1 ! y $end
$var reg 1 " clk $end
$var reg 1 # reset $end
$var reg 1 $ x $end
$scope module uut $end
$var wire 1 " clk $end
$var wire 1 # reset $end
$var wire 1 $ x $end
$var parameter 3 % s0 $end
$var parameter 3 & s1 $end
$var parameter 3 ' s2 $end
$var parameter 3 ( s3 $end
$var parameter 3 ) s4 $end
$var parameter 3 * s5 $end
$var parameter 3 + s6 $end
$var reg 3 , current_state [2:0] $end
$var reg 3 - next_state [2:0] $end
$var reg 1 ! y $end
$upscope $end
$upscope $end
$enddefinitions $end
$comment Show the parameter values. $end
$dumpall
b110 +
b101 *
b100 )
b11 (
b10 '
b1 &
b0 %
$end
#0
$dumpvars
b1 -
b0 ,
0$
0#
0"
0!
$end
#2
1#
#5
b1 ,
1"
#10
0"
#15
1"
#20
b10 -
1$
0"
#25
b0 -
b10 ,
1"
#30
b11 -
0$
0"
#35
b1 -
b11 ,
1"
#40
b100 -
1$
0"
#45
b0 -
b100 ,
1"
#50
b101 -
0$
0"
#55
b110 -
b101 ,
1"
#60
0"
#65
b1 -
b110 ,
1"
#70
1!
b10 -
1$
0"
#75
b0 -
0!
b10 ,
1"
#80
0"
#85
b0 ,
1"
