Verilog/II-semester/Draft/moore.v
module seq_det (
    x,y,clk,reset
);
    input x, clk, reset;
    output reg y;
    parameter s0 = 3'b000; // start
    parameter s1 = 3'b001; // 0
    parameter s2 = 3'b010; // 01
    parameter s3 = 3'b011; // 010
    parameter s4 = 3'b100; // 0101
    parameter s5 = 3'b101; // 01010
    parameter s6 = 3'b110; // 010100
    parameter s7 = 3'b111; // 0101001

    reg [2:0] current_state, next_state;

    always @(posedge clk or negedge reset) begin
        // if(!reset) begin
        //     current_state <= s0;
        // end
        // else begin
        //     current_state <= next_state;
        // end
        current_state <= (!reset) ? s0 : next_state;
    end

    always @(*) begin
        case (current_state)
            s0 : next_state = (x == 1'b0) ? s1 : s0;
            s1 : next_state = (x == 1'b1) ? s2 : s1;
            s2 : next_state = (x == 1'b0) ? s3 : s0;
            s3 : next_state = (x == 1'b1) ? s4 : s1;
            s4 : next_state = (x == 1'b0) ? s5 : s0;
            s5 : next_state = (x == 1'b0) ? s6 : s4;
            s6 : next_state = (x == 1'b1) ? s7 : s1;

            // Data overlap
            s7 : next_state = (x == 1'b0) ? s3 : s0; // s2 instead of s1
            default: next_state = s0;
        endcase
    end

    always @(*) begin
        y = (current_state == s7);
    end    
endmodule

module tb();
    reg x, clk, reset;
    wire y;

    seq_det uut(
        .x(x),
        .clk(clk),
        .reset(reset),
        .y(y)
    );

    always #5 clk = ~clk;

    initial begin
        clk = 0;
        reset = 0;
        x = 0;

        #12 reset = 1;
        
        @(negedge clk) x = 0;
        @(negedge clk) x = 1;
        @(negedge clk) x = 0;   
        @(negedge clk) x = 1;   
        @(negedge clk) x = 0;   
        @(negedge clk) x = 0;   
        @(negedge clk) x = 1;

        @(negedge clk) x = 0;   
        @(negedge clk) x = 0;
        
        #50;
        $display("Simulation is done");
        $finish;   
    end

    initial begin
        $monitor("Time=%0t | x=%b | state = %b | y=%b", $time, x, uut.current_state, y);
        $dumpfile("moore.vcd");
        $dumpvars(0, tb);
    end
endmodule

Verilog/II-semester/Draft/moore.vcd
$date
	Sun Mar  8 10:28:12 2026
$end
$version
	Icarus Verilog
$end
$timescale
	1s
$end
$scope module tb $end
$var wire 1 ! y $end
$var reg 1 " clk $end
$var reg 1 # reset $end
$var reg 1 $ x $end
$scope module uut $end
$var wire 1 " clk $end
$var wire 1 # reset $end
$var wire 1 $ x $end
$var parameter 3 % s0 $end
$var parameter 3 & s1 $end
$var parameter 3 ' s2 $end
$var parameter 3 ( s3 $end
$var parameter 3 ) s4 $end
$var parameter 3 * s5 $end
$var parameter 3 + s6 $end
$var parameter 3 , s7 $end
$var reg 3 - current_state [2:0] $end
$var reg 3 . next_state [2:0] $end
$var reg 1 ! y $end
$upscope $end
$upscope $end
$enddefinitions $end
$comment Show the parameter values. $end
$dumpall
b111 ,
b110 +
b101 *
b100 )
b11 (
b10 '
b1 &
b0 %
$end
#0
$dumpvars
b1 .
b0 -
0$
0#
0"
0!
$end
#5
1"
#10
0"
#12
1#
#15
b1 -
1"
#20
0"
#25
1"
#30
b10 .
1$
0"
#35
b0 .
b10 -
1"
#40
b11 .
0$
0"
#45
b1 .
b11 -
1"
#50
b100 .
1$
0"
#55
b0 .
b100 -
1"
#60
b101 .
0$
0"
#65
b110 .
b101 -
1"
#70
0"
#75
b1 .
b110 -
1"
#80
b111 .
1$
0"
#85
1!
b0 .
b111 -
1"
#90
b11 .
0$
0"
#95
0!
b1 .
b11 -
1"
#100
0"
#105
b1 -
1"
