Verilog/II-semester/Draft/task3.sv
module logic_cell(input a, b, c, output o);
    // // or(o, a & b | ~c, a & b & c);
    and(x, a, b);
    not(y, c);
    or(z, x, y);
    and(e, c, x);
    or(o, z, e);
endmodule

module logic_cell_tb();
    reg a;
    reg b;
    reg c;
    wire o;
    logic_cell dut(.a(a), .b(b), .c(c), .o(o));
    initial begin
    //    $display("i | a | b | c | out");
        $dumpfile("task3.vcd");
        $dumpvars(0, logic_cell_tb);
        for(integer i = 0; i < 8; i = i + 1) begin
            {a, b, c} = i[2:0]; 
            #5;
            $display("%d | a=%b | b=%b | c=%b | out=%b", i, a, b, c, o);
        end
        $finish;
    end
endmodule

Verilog/II-semester/Draft/task3.vcd
$date
	Tue Feb 24 22:58:29 2026
$end
$version
	Icarus Verilog
$end
$timescale
	1s
$end
$scope module logic_cell_tb $end
$var wire 1 ! o $end
$var reg 1 " a $end
$var reg 1 # b $end
$var reg 1 $ c $end
$scope module dut $end
$var wire 1 " a $end
$var wire 1 # b $end
$var wire 1 $ c $end
$var wire 1 % e $end
$var wire 1 ! o $end
$var wire 1 & x $end
$var wire 1 ' y $end
$var wire 1 ( z $end
$upscope $end
$scope begin $ivl_for_loop0 $end
$var integer 32 ) i [31:0] $end
$upscope $end
$upscope $end
$enddefinitions $end
$comment Show the parameter values. $end
$dumpall
$end
#0
$dumpvars
b0 )
1(
1'
0&
0%
0$
0#
0"
1!
$end
#5
0!
0(
0'
1$
b1 )
#10
1!
1(
1'
1#
0$
b10 )
#15
0!
0(
0'
1$
b11 )
#20
1!
1(
1'
1"
0#
0$
b100 )
#25
0!
0(
0'
1$
b101 )
#30
1!
1(
1&
1'
1#
0$
b110 )
#35
0'
1%
1$
b111 )
#40
b1000 )
